LICENSE
redisconfig/__init__.py
redisconfig/config.py
redisconfig/py.typed
redisconfig-0.1.1.dist-info/LICENSE
redisconfig-0.1.1.dist-info/WHEEL
redisconfig-0.1.1.dist-info/METADATA
redisconfig-0.1.1.dist-info/RECORD
