Metadata-Version: 2.1
Name: redisconfig
Version: 0.1.1
Summary: Simple, robust Redis configuration for Python
Home-page: https://github.com/xplor/redisconfig
License: MIT
Keywords: redis
Author: Jeremy Carbaugh
Author-email: jeremy.carbaugh@xplortechnologies.com
Requires-Python: >=3.6.2,<4.0.0
Classifier: License :: OSI Approved :: MIT License
Classifier: Programming Language :: Python :: 3
Classifier: Programming Language :: Python :: 3.10
Classifier: Programming Language :: Python :: 3.7
Classifier: Programming Language :: Python :: 3.8
Classifier: Programming Language :: Python :: 3.9
Provides-Extra: dev
Provides-Extra: test
Requires-Dist: black (==22.3.0); extra == "test" or extra == "dev"
Requires-Dist: dataclasses (>=0.8,<0.9); python_version == "3.6"
Requires-Dist: flake8 (>=4.0.1,<5.0.0); extra == "test" or extra == "dev"
Requires-Dist: mypy (>=0.920,<0.921); extra == "test" or extra == "dev"
Requires-Dist: pytest (>=6.2.5,<7.0.0); extra == "test" or extra == "dev"
Requires-Dist: redis (>=3,<5)
Project-URL: Repository, https://github.com/xplor/redisconfig
